lookup_plugins/__init__.py
lookup_plugins/__version__.py
lookup_plugins/onepassword_local.py
lookup_plugins/onepassword_local_test.py
ansible_1password_lookup_plugin-0.2.2.dist-info/LICENSE
ansible_1password_lookup_plugin-0.2.2.dist-info/METADATA
ansible_1password_lookup_plugin-0.2.2.dist-info/WHEEL
ansible_1password_lookup_plugin-0.2.2.dist-info/top_level.txt
ansible_1password_lookup_plugin-0.2.2.dist-info/RECORD
