Metadata-Version: 2.1
Name: ansible-1password-lookup-plugin
Version: 0.2.2
Summary: This is a simple lookup plugin that search for secrets in a local 1Password database (B5.sqlite format). It uses the onepassword-local-search python module that greatly improve performance over querying directly the 1Password servers.
Home-page: https://github.com/mickaelperrin/ansible-onepassword-local-lookup-plugin
Author: Mickaël Perrin
Author-email: dev@mickaelperrin.fr
License: GPLv3
Keywords: ansible onepassword 1password cli password secrets
Platform: UNKNOWN
Classifier: License :: OSI Approved :: GNU General Public License v3 or later (GPLv3+)
Classifier: Development Status :: 4 - Beta
Classifier: Environment :: Console
Classifier: Intended Audience :: Information Technology
Classifier: Natural Language :: French
Classifier: Topic :: Security
Classifier: Topic :: Security :: Cryptography
Classifier: Topic :: Utilities
Classifier: Programming Language :: Python
Classifier: Programming Language :: Python :: 3
Classifier: Programming Language :: Python :: 3.7
Classifier: Programming Language :: Python :: Implementation :: CPython
Classifier: Programming Language :: Python :: Implementation :: PyPy
Requires-Python: >=3.9.0
